staircase/__init__.py
staircase/_typing.py
staircase/constants.py
staircase/core/__init__.py
staircase/core/accessor.py
staircase/core/arrays/__init__.py
staircase/core/arrays/accessor.py
staircase/core/arrays/docstrings.py
staircase/core/arrays/extension.py
staircase/core/exceptions/__init__.py
staircase/core/layering.py
staircase/core/ops/__init__.py
staircase/core/ops/arithmetic.py
staircase/core/ops/common.py
staircase/core/ops/docstrings.py
staircase/core/ops/logical.py
staircase/core/ops/masking.py
staircase/core/ops/relational.py
staircase/core/ops/rops.py
staircase/core/sampling.py
staircase/core/slicing.py
staircase/core/stairs.py
staircase/core/stats/__init__.py
staircase/core/stats/distribution.py
staircase/core/stats/docstrings.py
staircase/core/stats/statistic.py
staircase/docstrings/__init__.py
staircase/docstrings/examples.py
staircase/docstrings/slicing.py
staircase/io/__init__.py
staircase/io/json.py
staircase/io/pickle.py
staircase/plotting/__init__.py
staircase/plotting/accessor.py
staircase/plotting/docstrings.py
staircase/plotting/matplotlib.py
staircase/test_data.py
staircase/util/__init__.py
staircase/util/_decorators.py
staircase-2.7.0.dist-info/LICENSE
staircase-2.7.0.dist-info/METADATA
staircase-2.7.0.dist-info/WHEEL
staircase-2.7.0.dist-info/RECORD
