Metadata-Version: 2.1
Name: staircase
Version: 2.7.0
Summary: A data analysis package based on modelling and manipulation of mathematical step functions. Strongly aligned with pandas.
Home-page: https://staircase.dev
License: MIT
Keywords: Staircase,Step Functions,Mathematics,Data Analysis,Analysis,Data Structures,Time Signal,Simulation Output
Author: Riley Clement
Author-email: venaturum@gmail.com
Maintainer: Riley Clement
Maintainer-email: venaturum@gmail.com
Requires-Python: >=3.9,<4.0
Classifier: Intended Audience :: Science/Research
Classifier: License :: OSI Approved :: MIT License
Classifier: Operating System :: OS Independent
Classifier: Programming Language :: Python :: 3
Classifier: Programming Language :: Python :: 3.9
Classifier: Programming Language :: Python :: 3.10
Classifier: Programming Language :: Python :: 3.11
Classifier: Programming Language :: Python :: 3.12
Classifier: Programming Language :: Python :: 3.13
Classifier: Topic :: Scientific/Engineering
Provides-Extra: codecov
Requires-Dist: matplotlib (>=2) ; python_version >= "3.8" and python_version < "3.11"
Requires-Dist: matplotlib (>=3.6,<4.0) ; python_version >= "3.11" and python_version < "4.0"
Requires-Dist: numpy (>=1.16,<2.0) ; python_version >= "3.8" and python_version < "3.10"
Requires-Dist: numpy (>=1.21.2,<3) ; python_version >= "3.10" and python_version < "4.0"
Requires-Dist: pandas (>=1,<2) ; python_version >= "3.8" and python_version < "3.10"
Requires-Dist: pandas (>=1.3.4,<3) ; python_version >= "3.10" and python_version < "4.0"
Requires-Dist: pytz
Requires-Dist: typing-extensions (>=4.4.0,<5.0.0)
Project-URL: Bug Tracker, https://github.com/staircase-dev/staircase/issues
Project-URL: Documentation, https://staircase.dev
Project-URL: Repository, https://github.com/staircase-dev/staircase
